pymul/__init__.py
pymul/network.py
pymul/functions/__init__.py
pymul/functions/activation.py
pymul/functions/loss.py
pymul/layers/activation_layer.py
pymul/layers/layer.py
pymul/layers/neuron_layer.py
pymul-0.0.1.dist-info/LICENSE
pymul-0.0.1.dist-info/METADATA
pymul-0.0.1.dist-info/WHEEL
pymul-0.0.1.dist-info/top_level.txt
pymul-0.0.1.dist-info/RECORD
