Metadata-Version: 2.1
Name: pymul
Version: 0.0.1
Summary: A Python machine learning library!
Home-page: https://github.com/mathletedev/pymul
Author: mathletedev
Author-email: mathletedev@gmail.com
License: Apache License 2.0
Platform: UNKNOWN
Requires-Dist: numpy (>=1.20.2)
